Metadata-Version: 2.1
Name: pyMicroCode
Version: 7.0.0
Summary: generate microcode(these are sort of like qrcode but have someother uses)
Home-page: https://github.com/mastercodermerwin/pyMicroCode
Author: Cactochan
License: UNKNOWN
Project-URL: Bug Tracker, https://github.com/mastercodermerwin/pyMicroCode/issues
Platform: UNKNOWN
Classifier: Programming Language :: Python :: 3
Classifier: License :: OSI Approved :: MIT License
Classifier: Operating System :: OS Independent
License-File: LICENSE.txt
